langsmith_mcp_server-0.0.9.dist-info/METADATA
langsmith_mcp_server-0.0.9.dist-info/WHEEL
langsmith_mcp_server-0.0.9.dist-info/entry_points.txt
langsmith_mcp_server-0.0.9.dist-info/licenses/LICENSE
langsmith_mcp_server/__init__.py
langsmith_mcp_server/common/__init__.py
langsmith_mcp_server/common/helpers.py
langsmith_mcp_server/middleware.py
langsmith_mcp_server/server.py
langsmith_mcp_server/services/__init__.py
langsmith_mcp_server/services/prompts/__init__.py
langsmith_mcp_server/services/register_prompts.py
langsmith_mcp_server/services/register_resources.py
langsmith_mcp_server/services/register_tools.py
langsmith_mcp_server/services/resources/__init__.py
langsmith_mcp_server/services/resources/langgraph_docs.py
langsmith_mcp_server/services/resources/langsmith_docs.py
langsmith_mcp_server/services/tools/__init__.py
langsmith_mcp_server/services/tools/datasets.py
langsmith_mcp_server/services/tools/experiments.py
langsmith_mcp_server/services/tools/prompts.py
langsmith_mcp_server/services/tools/traces.py
langsmith_mcp_server/services/tools/workspaces.py
langsmith_mcp_server-0.0.9.dist-info/RECORD
