Metadata-Version: 2.4
Name: langsmith-mcp-server
Version: 0.0.9
Summary: MCP server for Langsmith SDK integration
Author-Email: Marco Perini <oss@langchain.dev>
License-Expression: MIT
Project-URL: Homepage, https://github.com/langchain-ai/langsmith-mcp-server
Project-URL: Bug Tracker, https://github.com/langchain-ai/langsmith-mcp-server/issues
Requires-Python: >=3.10
Requires-Dist: fastmcp>=2.13
Requires-Dist: langsmith>=0.4.42
Requires-Dist: langchain-core>=0.3.56
Requires-Dist: uvicorn>=0.34.0
